usbserial.py
USBSerial-1.1.0.dist-info/LICENSE
USBSerial-1.1.0.dist-info/METADATA
USBSerial-1.1.0.dist-info/WHEEL
USBSerial-1.1.0.dist-info/top_level.txt
USBSerial-1.1.0.dist-info/RECORD
