Metadata-Version: 2.1
Name: USBSerial
Version: 1.1.0
Summary: HC-USBSerial Python library via Serial protocol, using pySerial library as API
Home-page: https://github.com/KKimj/USBSerial_Python-library
Author: KKimj
Author-email: kkimj@hanyang.ac.kr
License: GPL-3.0 License
Platform: UNKNOWN
Classifier: Programming Language :: Python :: 3
Classifier: License :: OSI Approved :: GNU General Public License v3 (GPLv3)
Classifier: Operating System :: OS Independent
Classifier: Topic :: Terminals :: Serial
Classifier: Natural Language :: Korean
Requires-Python: >=3
